{"time":{"updated":"Sep 14, 2024 18:27:53 UTC","updatedISO":"2024-09-14T18:27:53+00:00","updateduk":"Sep 14, 2024 at 19:27 BST"},"disclaimer":"This data was produced from the CoinDesk Bitcoin Price Index (USD). Non-USD currency data converted using hourly conversion rate from openexchangerates.org","chartName":"Bitcoin","bpi":{"USD":{"code":"USD","symbol":"&#36;","rate":"59,715.048","description":"United States Dollar","rate_float":59715.0482},"GBP":{"code":"GBP","symbol":"&pound;","rate":"45,502.389","description":"British Pound Sterling","rate_float":45502.389},"EUR":{"code":"EUR","symbol":"&euro;","rate":"53,882.262","description":"Euro","rate_float":53882.2615},"CNY":{"code":"CNY","symbol":"&yen;","rate":"423,588.695","description":"Chinese Yuan","rate_float":423588.6946}}}