{"time":{"updated":"Jul 24, 2024 11:40:52 UTC","updatedISO":"2024-07-24T11:40:52+00:00","updateduk":"Jul 24, 2024 at 12:40 BST"},"disclaimer":"This data was produced from the CoinDesk Bitcoin Price Index (USD). Non-USD currency data converted using hourly conversion rate from openexchangerates.org","chartName":"Bitcoin","bpi":{"USD":{"code":"USD","symbol":"&#36;","rate":"66,423.455","description":"United States Dollar","rate_float":66423.455},"GBP":{"code":"GBP","symbol":"&pound;","rate":"51,464.096","description":"British Pound Sterling","rate_float":51464.0959},"EUR":{"code":"EUR","symbol":"&euro;","rate":"61,262.552","description":"Euro","rate_float":61262.5518},"CNY":{"code":"CNY","symbol":"&yen;","rate":"483,376.767","description":"Chinese Yuan","rate_float":483376.7669}}}