{"time":{"updated":"Sep 17, 2024 15:41:09 UTC","updatedISO":"2024-09-17T15:41:09+00:00","updateduk":"Sep 17, 2024 at 16:41 BST"},"disclaimer":"This data was produced from the CoinDesk Bitcoin Price Index (USD). Non-USD currency data converted using hourly conversion rate from openexchangerates.org","chartName":"Bitcoin","bpi":{"USD":{"code":"USD","symbol":"&#36;","rate":"61,065.72","description":"United States Dollar","rate_float":61065.7197},"GBP":{"code":"GBP","symbol":"&pound;","rate":"46,306.074","description":"British Pound Sterling","rate_float":46306.0742},"EUR":{"code":"EUR","symbol":"&euro;","rate":"54,891.548","description":"Euro","rate_float":54891.548},"CNY":{"code":"CNY","symbol":"&yen;","rate":"433,163.576","description":"Chinese Yuan","rate_float":433163.5764}}}