{"time":{"updated":"Mar 25, 2023 20:19:00 UTC","updatedISO":"2023-03-25T20:19:00+00:00","updateduk":"Mar 25, 2023 at 20:19 GMT"},"disclaimer":"This data was produced from the CoinDesk Bitcoin Price Index (USD). Non-USD currency data converted using hourly conversion rate from openexchangerates.org","chartName":"Bitcoin","bpi":{"USD":{"code":"USD","symbol":"&#36;","rate":"27,341.9108","description":"United States Dollar","rate_float":27341.9108},"GBP":{"code":"GBP","symbol":"&pound;","rate":"22,846.6819","description":"British Pound Sterling","rate_float":22846.6819},"EUR":{"code":"EUR","symbol":"&euro;","rate":"26,635.0130","description":"Euro","rate_float":26635.013},"CNY":{"code":"CNY","symbol":"&yen;","rate":"40,202.5000","description":"Chinese Yuan","rate_float":40202.5}}}