{"time":{"updated":"Mar 9, 2023 23:24:00 UTC","updatedISO":"2023-03-09T23:24:00+00:00","updateduk":"Mar 9, 2023 at 23:24 GMT"},"disclaimer":"This data was produced from the CoinDesk Bitcoin Price Index (USD). Non-USD currency data converted using hourly conversion rate from openexchangerates.org","chartName":"Bitcoin","bpi":{"USD":{"code":"USD","symbol":"&#36;","rate":"20,354.0778","description":"United States Dollar","rate_float":20354.0778},"GBP":{"code":"GBP","symbol":"&pound;","rate":"17,007.7046","description":"British Pound Sterling","rate_float":17007.7046},"EUR":{"code":"EUR","symbol":"&euro;","rate":"19,827.8435","description":"Euro","rate_float":19827.8435},"CNY":{"code":"CNY","symbol":"&yen;","rate":"40,202.5000","description":"Chinese Yuan","rate_float":40202.5}}}