{"time":{"updated":"Oct 28, 2024 13:37:39 UTC","updatedISO":"2024-10-28T13:37:39+00:00","updateduk":"Oct 28, 2024 at 13:37 GMT"},"disclaimer":"This data was produced from the CoinDesk Bitcoin Price Index (USD). Non-USD currency data converted using hourly conversion rate from openexchangerates.org","chartName":"Bitcoin","bpi":{"USD":{"code":"USD","symbol":"&#36;","rate":"68,887.296","description":"United States Dollar","rate_float":68887.2963},"GBP":{"code":"GBP","symbol":"&pound;","rate":"53,038.396","description":"British Pound Sterling","rate_float":53038.396},"EUR":{"code":"EUR","symbol":"&euro;","rate":"63,691.265","description":"Euro","rate_float":63691.2653},"CNY":{"code":"CNY","symbol":"&yen;","rate":"490,945.983","description":"Chinese Yuan","rate_float":490945.9833}}}