{"time":{"updated":"Aug 3, 2024 04:55:03 UTC","updatedISO":"2024-08-03T04:55:03+00:00","updateduk":"Aug 3, 2024 at 05:55 BST"},"disclaimer":"This data was produced from the CoinDesk Bitcoin Price Index (USD). Non-USD currency data converted using hourly conversion rate from openexchangerates.org","chartName":"Bitcoin","bpi":{"USD":{"code":"USD","symbol":"&#36;","rate":"61,603.443","description":"United States Dollar","rate_float":61603.4434},"GBP":{"code":"GBP","symbol":"&pound;","rate":"48,105.143","description":"British Pound Sterling","rate_float":48105.1433},"EUR":{"code":"EUR","symbol":"&euro;","rate":"56,431.526","description":"Euro","rate_float":56431.5263},"CNY":{"code":"CNY","symbol":"&yen;","rate":"441,031.372","description":"Chinese Yuan","rate_float":441031.372}}}