{"time":{"updated":"Apr 9, 2024 06:22:00 UTC","updatedISO":"2024-04-09T06:22:00+00:00","updateduk":"Apr 9, 2024 at 07:22 BST"},"disclaimer":"This data was produced from the CoinDesk Bitcoin Price Index (USD). Non-USD currency data converted using hourly conversion rate from openexchangerates.org","chartName":"Bitcoin","bpi":{"USD":{"code":"USD","symbol":"&#36;","rate":"71,003.157","description":"United States Dollar","rate_float":71003.1568},"GBP":{"code":"GBP","symbol":"&pound;","rate":"56,098.955","description":"British Pound Sterling","rate_float":56098.9551},"EUR":{"code":"EUR","symbol":"&euro;","rate":"65,400.937","description":"Euro","rate_float":65400.9367},"CNY":{"code":"CNY","symbol":"&yen;","rate":"513,651.037","description":"Chinese Yuan","rate_float":513651.0367}}}