{"time":{"updated":"May 12, 2024 06:19:26 UTC","updatedISO":"2024-05-12T06:19:26+00:00","updateduk":"May 12, 2024 at 07:19 BST"},"disclaimer":"This data was produced from the CoinDesk Bitcoin Price Index (USD). Non-USD currency data converted using hourly conversion rate from openexchangerates.org","chartName":"Bitcoin","bpi":{"USD":{"code":"USD","symbol":"&#36;","rate":"61,077.794","description":"United States Dollar","rate_float":61077.7939},"GBP":{"code":"GBP","symbol":"&pound;","rate":"48,768.603","description":"British Pound Sterling","rate_float":48768.6029},"EUR":{"code":"EUR","symbol":"&euro;","rate":"56,664.923","description":"Euro","rate_float":56664.9233},"CNY":{"code":"CNY","symbol":"&yen;","rate":"441,390.894","description":"Chinese Yuan","rate_float":441390.8935}}}