{"time":{"updated":"May 14, 2024 02:52:13 UTC","updatedISO":"2024-05-14T02:52:13+00:00","updateduk":"May 14, 2024 at 03:52 BST"},"disclaimer":"This data was produced from the CoinDesk Bitcoin Price Index (USD). Non-USD currency data converted using hourly conversion rate from openexchangerates.org","chartName":"Bitcoin","bpi":{"USD":{"code":"USD","symbol":"&#36;","rate":"62,608.098","description":"United States Dollar","rate_float":62608.0983},"GBP":{"code":"GBP","symbol":"&pound;","rate":"49,859.775","description":"British Pound Sterling","rate_float":49859.7747},"EUR":{"code":"EUR","symbol":"&euro;","rate":"58,037.832","description":"Euro","rate_float":58037.8323},"CNY":{"code":"CNY","symbol":"&yen;","rate":"453,119.851","description":"Chinese Yuan","rate_float":453119.8506}}}