{"time":{"updated":"Jan 24, 2024 09:39:10 UTC","updatedISO":"2024-01-24T09:39:10+00:00","updateduk":"Jan 24, 2024 at 09:39 GMT"},"disclaimer":"This data was produced from the CoinDesk Bitcoin Price Index (USD). Non-USD currency data converted using hourly conversion rate from openexchangerates.org","chartName":"Bitcoin","bpi":{"USD":{"code":"USD","symbol":"&#36;","rate":"39,923.68","description":"United States Dollar","rate_float":39923.6801},"GBP":{"code":"GBP","symbol":"&pound;","rate":"31,413.069","description":"British Pound Sterling","rate_float":31413.0694},"EUR":{"code":"EUR","symbol":"&euro;","rate":"36,729.107","description":"Euro","rate_float":36729.107},"CNY":{"code":"CNY","symbol":"&yen;","rate":"282,979.044","description":"Chinese Yuan","rate_float":282979.0444}}}