{"time":{"updated":"Nov 20, 2024 22:39:17 UTC","updatedISO":"2024-11-20T22:39:17+00:00","updateduk":"Nov 20, 2024 at 22:39 GMT"},"disclaimer":"This data was produced from the CoinDesk Bitcoin Price Index (USD). Non-USD currency data converted using hourly conversion rate from openexchangerates.org","chartName":"Bitcoin","bpi":{"USD":{"code":"USD","symbol":"&#36;","rate":"94,052.954","description":"United States Dollar","rate_float":94052.9543},"GBP":{"code":"GBP","symbol":"&pound;","rate":"74,334.564","description":"British Pound Sterling","rate_float":74334.5643},"EUR":{"code":"EUR","symbol":"&euro;","rate":"89,201.327","description":"Euro","rate_float":89201.3267},"CNY":{"code":"CNY","symbol":"&yen;","rate":"681,420.238","description":"Chinese Yuan","rate_float":681420.2376}}}