{"time":{"updated":"Aug 14, 2023 16:36:00 UTC","updatedISO":"2023-08-14T16:36:00+00:00","updateduk":"Aug 14, 2023 at 17:36 BST"},"disclaimer":"This data was produced from the CoinDesk Bitcoin Price Index (USD). Non-USD currency data converted using hourly conversion rate from openexchangerates.org","chartName":"Bitcoin","bpi":{"USD":{"code":"USD","symbol":"&#36;","rate":"29,598.4583","description":"United States Dollar","rate_float":29598.4583},"GBP":{"code":"GBP","symbol":"&pound;","rate":"24,732.2350","description":"British Pound Sterling","rate_float":24732.235},"EUR":{"code":"EUR","symbol":"&euro;","rate":"28,833.2198","description":"Euro","rate_float":28833.2198},"CNY":{"code":"CNY","symbol":"&yen;","rate":"40,202.5000","description":"Chinese Yuan","rate_float":40202.5}}}