{"time":{"updated":"Jan 7, 2025 07:00:12 UTC","updatedISO":"2025-01-07T07:00:12+00:00","updateduk":"Jan 7, 2025 at 07:00 GMT"},"disclaimer":"This data was produced from the CoinDesk Bitcoin Price Index (USD). Non-USD currency data converted using hourly conversion rate from openexchangerates.org","chartName":"Bitcoin","bpi":{"USD":{"code":"USD","symbol":"&#36;","rate":"101,846.965","description":"United States Dollar","rate_float":101846.965},"GBP":{"code":"GBP","symbol":"&pound;","rate":"81,231.917","description":"British Pound Sterling","rate_float":81231.9171},"EUR":{"code":"EUR","symbol":"&euro;","rate":"97,960.892","description":"Euro","rate_float":97960.8922},"CNY":{"code":"CNY","symbol":"&yen;","rate":"746,069.757","description":"Chinese Yuan","rate_float":746069.7571}}}