{"time":{"updated":"Jun 7, 2023 10:28:00 UTC","updatedISO":"2023-06-07T10:28:00+00:00","updateduk":"Jun 7, 2023 at 11:28 BST"},"disclaimer":"This data was produced from the CoinDesk Bitcoin Price Index (USD). Non-USD currency data converted using hourly conversion rate from openexchangerates.org","chartName":"Bitcoin","bpi":{"USD":{"code":"USD","symbol":"&#36;","rate":"26,531.4010","description":"United States Dollar","rate_float":26531.401},"GBP":{"code":"GBP","symbol":"&pound;","rate":"22,169.4264","description":"British Pound Sterling","rate_float":22169.4264},"EUR":{"code":"EUR","symbol":"&euro;","rate":"25,845.4582","description":"Euro","rate_float":25845.4582},"CNY":{"code":"CNY","symbol":"&yen;","rate":"40,202.5000","description":"Chinese Yuan","rate_float":40202.5}}}