{"time":{"updated":"Jul 19, 2024 03:46:19 UTC","updatedISO":"2024-07-19T03:46:19+00:00","updateduk":"Jul 19, 2024 at 04:46 BST"},"disclaimer":"This data was produced from the CoinDesk Bitcoin Price Index (USD). Non-USD currency data converted using hourly conversion rate from openexchangerates.org","chartName":"Bitcoin","bpi":{"USD":{"code":"USD","symbol":"&#36;","rate":"64,314.152","description":"United States Dollar","rate_float":64314.1519},"GBP":{"code":"GBP","symbol":"&pound;","rate":"49,686.091","description":"British Pound Sterling","rate_float":49686.091},"EUR":{"code":"EUR","symbol":"&euro;","rate":"59,046.759","description":"Euro","rate_float":59046.7586},"CNY":{"code":"CNY","symbol":"&yen;","rate":"467,358.079","description":"Chinese Yuan","rate_float":467358.0791}}}