{"time":{"updated":"Apr 14, 2024 23:37:20 UTC","updatedISO":"2024-04-14T23:37:20+00:00","updateduk":"Apr 15, 2024 at 00:37 BST"},"disclaimer":"This data was produced from the CoinDesk Bitcoin Price Index (USD). Non-USD currency data converted using hourly conversion rate from openexchangerates.org","chartName":"Bitcoin","bpi":{"USD":{"code":"USD","symbol":"&#36;","rate":"65,763.944","description":"United States Dollar","rate_float":65763.9439},"GBP":{"code":"GBP","symbol":"&pound;","rate":"52,780.103","description":"British Pound Sterling","rate_float":52780.1027},"EUR":{"code":"EUR","symbol":"&euro;","rate":"61,751.16","description":"Euro","rate_float":61751.1596},"CNY":{"code":"CNY","symbol":"&yen;","rate":"472,329.798","description":"Chinese Yuan","rate_float":472329.7982}}}