{"time":{"updated":"Jan 14, 2024 22:49:50 UTC","updatedISO":"2024-01-14T22:49:50+00:00","updateduk":"Jan 14, 2024 at 22:49 GMT"},"disclaimer":"This data was produced from the CoinDesk Bitcoin Price Index (USD). Non-USD currency data converted using hourly conversion rate from openexchangerates.org","chartName":"Bitcoin","bpi":{"USD":{"code":"USD","symbol":"&#36;","rate":"42,333.416","description":"United States Dollar","rate_float":42333.4164},"GBP":{"code":"GBP","symbol":"&pound;","rate":"33,206.459","description":"British Pound Sterling","rate_float":33206.4588},"EUR":{"code":"EUR","symbol":"&euro;","rate":"38,645.16","description":"Euro","rate_float":38645.1598},"CNY":{"code":"CNY","symbol":"&yen;","rate":"301,032.924","description":"Chinese Yuan","rate_float":301032.9237}}}