{"time":{"updated":"May 27, 2024 09:52:23 UTC","updatedISO":"2024-05-27T09:52:23+00:00","updateduk":"May 27, 2024 at 10:52 BST"},"disclaimer":"This data was produced from the CoinDesk Bitcoin Price Index (USD). Non-USD currency data converted using hourly conversion rate from openexchangerates.org","chartName":"Bitcoin","bpi":{"USD":{"code":"USD","symbol":"&#36;","rate":"68,609.201","description":"United States Dollar","rate_float":68609.201},"GBP":{"code":"GBP","symbol":"&pound;","rate":"53,843.746","description":"British Pound Sterling","rate_float":53843.7463},"EUR":{"code":"EUR","symbol":"&euro;","rate":"63,232.024","description":"Euro","rate_float":63232.0235},"CNY":{"code":"CNY","symbol":"&yen;","rate":"497,046.218","description":"Chinese Yuan","rate_float":497046.2177}}}