{"time":{"updated":"Dec 23, 2024 11:21:52 UTC","updatedISO":"2024-12-23T11:21:52+00:00","updateduk":"Dec 23, 2024 at 11:21 GMT"},"disclaimer":"This data was produced from the CoinDesk Bitcoin Price Index (USD). Non-USD currency data converted using hourly conversion rate from openexchangerates.org","chartName":"Bitcoin","bpi":{"USD":{"code":"USD","symbol":"&#36;","rate":"96,056.233","description":"United States Dollar","rate_float":96056.2334},"GBP":{"code":"GBP","symbol":"&pound;","rate":"76,821.933","description":"British Pound Sterling","rate_float":76821.9333},"EUR":{"code":"EUR","symbol":"&euro;","rate":"92,514.832","description":"Euro","rate_float":92514.8322},"CNY":{"code":"CNY","symbol":"&yen;","rate":"701,133.659","description":"Chinese Yuan","rate_float":701133.6592}}}