{"time":{"updated":"Aug 30, 2024 13:43:05 UTC","updatedISO":"2024-08-30T13:43:05+00:00","updateduk":"Aug 30, 2024 at 14:43 BST"},"disclaimer":"This data was produced from the CoinDesk Bitcoin Price Index (USD). Non-USD currency data converted using hourly conversion rate from openexchangerates.org","chartName":"Bitcoin","bpi":{"USD":{"code":"USD","symbol":"&#36;","rate":"59,501.837","description":"United States Dollar","rate_float":59501.8373},"GBP":{"code":"GBP","symbol":"&pound;","rate":"45,227.347","description":"British Pound Sterling","rate_float":45227.3465},"EUR":{"code":"EUR","symbol":"&euro;","rate":"53,756.518","description":"Euro","rate_float":53756.5184},"CNY":{"code":"CNY","symbol":"&yen;","rate":"421,772.823","description":"Chinese Yuan","rate_float":421772.8233}}}