{"time":{"updated":"Apr 26, 2024 06:52:27 UTC","updatedISO":"2024-04-26T06:52:27+00:00","updateduk":"Apr 26, 2024 at 07:52 BST"},"disclaimer":"This data was produced from the CoinDesk Bitcoin Price Index (USD). Non-USD currency data converted using hourly conversion rate from openexchangerates.org","chartName":"Bitcoin","bpi":{"USD":{"code":"USD","symbol":"&#36;","rate":"64,455.131","description":"United States Dollar","rate_float":64455.1309},"GBP":{"code":"GBP","symbol":"&pound;","rate":"51,542.254","description":"British Pound Sterling","rate_float":51542.2544},"EUR":{"code":"EUR","symbol":"&euro;","rate":"60,091.776","description":"Euro","rate_float":60091.7763},"CNY":{"code":"CNY","symbol":"&yen;","rate":"467,054.769","description":"Chinese Yuan","rate_float":467054.7692}}}