{"time":{"updated":"Mar 20, 2024 23:47:04 UTC","updatedISO":"2024-03-20T23:47:04+00:00","updateduk":"Mar 20, 2024 at 23:47 GMT"},"disclaimer":"This data was produced from the CoinDesk Bitcoin Price Index (USD). Non-USD currency data converted using hourly conversion rate from openexchangerates.org","chartName":"Bitcoin","bpi":{"USD":{"code":"USD","symbol":"&#36;","rate":"67,762.801","description":"United States Dollar","rate_float":67762.8006},"GBP":{"code":"GBP","symbol":"&pound;","rate":"52,969.233","description":"British Pound Sterling","rate_float":52969.2326},"EUR":{"code":"EUR","symbol":"&euro;","rate":"61,981.888","description":"Euro","rate_float":61981.8883},"CNY":{"code":"CNY","symbol":"&yen;","rate":"487,783.744","description":"Chinese Yuan","rate_float":487783.7439}}}