{"time":{"updated":"Aug 8, 2024 23:40:14 UTC","updatedISO":"2024-08-08T23:40:14+00:00","updateduk":"Aug 9, 2024 at 00:40 BST"},"disclaimer":"This data was produced from the CoinDesk Bitcoin Price Index (USD). Non-USD currency data converted using hourly conversion rate from openexchangerates.org","chartName":"Bitcoin","bpi":{"USD":{"code":"USD","symbol":"&#36;","rate":"61,966.055","description":"United States Dollar","rate_float":61966.0545},"GBP":{"code":"GBP","symbol":"&pound;","rate":"48,626.932","description":"British Pound Sterling","rate_float":48626.9318},"EUR":{"code":"EUR","symbol":"&euro;","rate":"56,752.726","description":"Euro","rate_float":56752.7264},"CNY":{"code":"CNY","symbol":"&yen;","rate":"444,594.048","description":"Chinese Yuan","rate_float":444594.0479}}}