{"time":{"updated":"Dec 5, 2024 19:45:08 UTC","updatedISO":"2024-12-05T19:45:08+00:00","updateduk":"Dec 5, 2024 at 19:45 GMT"},"disclaimer":"This data was produced from the CoinDesk Bitcoin Price Index (USD). Non-USD currency data converted using hourly conversion rate from openexchangerates.org","chartName":"Bitcoin","bpi":{"USD":{"code":"USD","symbol":"&#36;","rate":"99,747.625","description":"United States Dollar","rate_float":99747.6246},"GBP":{"code":"GBP","symbol":"&pound;","rate":"78,292.21","description":"British Pound Sterling","rate_float":78292.2098},"EUR":{"code":"EUR","symbol":"&euro;","rate":"94,386.19","description":"Euro","rate_float":94386.1898},"CNY":{"code":"CNY","symbol":"&yen;","rate":"724,157.78","description":"Chinese Yuan","rate_float":724157.7799}}}