{"time":{"updated":"Jul 13, 2024 23:17:31 UTC","updatedISO":"2024-07-13T23:17:31+00:00","updateduk":"Jul 14, 2024 at 00:17 BST"},"disclaimer":"This data was produced from the CoinDesk Bitcoin Price Index (USD). Non-USD currency data converted using hourly conversion rate from openexchangerates.org","chartName":"Bitcoin","bpi":{"USD":{"code":"USD","symbol":"&#36;","rate":"59,652.579","description":"United States Dollar","rate_float":59652.5787},"GBP":{"code":"GBP","symbol":"&pound;","rate":"45,965.891","description":"British Pound Sterling","rate_float":45965.891},"EUR":{"code":"EUR","symbol":"&euro;","rate":"54,624.403","description":"Euro","rate_float":54624.4032},"CNY":{"code":"CNY","symbol":"&yen;","rate":"432,505.057","description":"Chinese Yuan","rate_float":432505.0566}}}