{"time":{"updated":"Mar 28, 2024 22:54:51 UTC","updatedISO":"2024-03-28T22:54:51+00:00","updateduk":"Mar 28, 2024 at 22:54 GMT"},"disclaimer":"This data was produced from the CoinDesk Bitcoin Price Index (USD). Non-USD currency data converted using hourly conversion rate from openexchangerates.org","chartName":"Bitcoin","bpi":{"USD":{"code":"USD","symbol":"&#36;","rate":"70,877.569","description":"United States Dollar","rate_float":70877.5693},"GBP":{"code":"GBP","symbol":"&pound;","rate":"56,157.999","description":"British Pound Sterling","rate_float":56157.9992},"EUR":{"code":"EUR","symbol":"&euro;","rate":"65,695.214","description":"Euro","rate_float":65695.2141},"CNY":{"code":"CNY","symbol":"&yen;","rate":"512,260.545","description":"Chinese Yuan","rate_float":512260.5446}}}