{"time":{"updated":"Jul 24, 2024 06:42:48 UTC","updatedISO":"2024-07-24T06:42:48+00:00","updateduk":"Jul 24, 2024 at 07:42 BST"},"disclaimer":"This data was produced from the CoinDesk Bitcoin Price Index (USD). Non-USD currency data converted using hourly conversion rate from openexchangerates.org","chartName":"Bitcoin","bpi":{"USD":{"code":"USD","symbol":"&#36;","rate":"65,900.651","description":"United States Dollar","rate_float":65900.6511},"GBP":{"code":"GBP","symbol":"&pound;","rate":"51,107.009","description":"British Pound Sterling","rate_float":51107.0093},"EUR":{"code":"EUR","symbol":"&euro;","rate":"60,724.748","description":"Euro","rate_float":60724.7481},"CNY":{"code":"CNY","symbol":"&yen;","rate":"479,387.696","description":"Chinese Yuan","rate_float":479387.6964}}}