{"time":{"updated":"May 16, 2024 10:58:19 UTC","updatedISO":"2024-05-16T10:58:19+00:00","updateduk":"May 16, 2024 at 11:58 BST"},"disclaimer":"This data was produced from the CoinDesk Bitcoin Price Index (USD). Non-USD currency data converted using hourly conversion rate from openexchangerates.org","chartName":"Bitcoin","bpi":{"USD":{"code":"USD","symbol":"&#36;","rate":"66,206.831","description":"United States Dollar","rate_float":66206.831},"GBP":{"code":"GBP","symbol":"&pound;","rate":"52,263.01","description":"British Pound Sterling","rate_float":52263.0103},"EUR":{"code":"EUR","symbol":"&euro;","rate":"60,907.636","description":"Euro","rate_float":60907.6362},"CNY":{"code":"CNY","symbol":"&yen;","rate":"477,927.251","description":"Chinese Yuan","rate_float":477927.2509}}}