{"time":{"updated":"Jul 6, 2023 08:47:00 UTC","updatedISO":"2023-07-06T08:47:00+00:00","updateduk":"Jul 6, 2023 at 09:47 BST"},"disclaimer":"This data was produced from the CoinDesk Bitcoin Price Index (USD). Non-USD currency data converted using hourly conversion rate from openexchangerates.org","chartName":"Bitcoin","bpi":{"USD":{"code":"USD","symbol":"&#36;","rate":"31,077.7442","description":"United States Dollar","rate_float":31077.7442},"GBP":{"code":"GBP","symbol":"&pound;","rate":"25,968.3144","description":"British Pound Sterling","rate_float":25968.3144},"EUR":{"code":"EUR","symbol":"&euro;","rate":"30,274.2602","description":"Euro","rate_float":30274.2602},"CNY":{"code":"CNY","symbol":"&yen;","rate":"40,202.5000","description":"Chinese Yuan","rate_float":40202.5}}}