{"time":{"updated":"Sep 1, 2024 02:45:43 UTC","updatedISO":"2024-09-01T02:45:43+00:00","updateduk":"Sep 1, 2024 at 03:45 BST"},"disclaimer":"This data was produced from the CoinDesk Bitcoin Price Index (USD). Non-USD currency data converted using hourly conversion rate from openexchangerates.org","chartName":"Bitcoin","bpi":{"USD":{"code":"USD","symbol":"&#36;","rate":"58,500.648","description":"United States Dollar","rate_float":58500.6484},"GBP":{"code":"GBP","symbol":"&pound;","rate":"44,553.275","description":"British Pound Sterling","rate_float":44553.2748},"EUR":{"code":"EUR","symbol":"&euro;","rate":"52,891.489","description":"Euro","rate_float":52891.4893},"CNY":{"code":"CNY","symbol":"&yen;","rate":"414,950.949","description":"Chinese Yuan","rate_float":414950.9493}}}