{"time":{"updated":"Jul 9, 2024 19:08:34 UTC","updatedISO":"2024-07-09T19:08:34+00:00","updateduk":"Jul 9, 2024 at 20:08 BST"},"disclaimer":"This data was produced from the CoinDesk Bitcoin Price Index (USD). Non-USD currency data converted using hourly conversion rate from openexchangerates.org","chartName":"Bitcoin","bpi":{"USD":{"code":"USD","symbol":"&#36;","rate":"57,784.892","description":"United States Dollar","rate_float":57784.8924},"GBP":{"code":"GBP","symbol":"&pound;","rate":"45,205.873","description":"British Pound Sterling","rate_float":45205.8726},"EUR":{"code":"EUR","symbol":"&euro;","rate":"53,459.462","description":"Euro","rate_float":53459.4621},"CNY":{"code":"CNY","symbol":"&yen;","rate":"420,234.852","description":"Chinese Yuan","rate_float":420234.8518}}}