{"time":{"updated":"Sep 3, 2024 23:17:10 UTC","updatedISO":"2024-09-03T23:17:10+00:00","updateduk":"Sep 4, 2024 at 00:17 BST"},"disclaimer":"This data was produced from the CoinDesk Bitcoin Price Index (USD). Non-USD currency data converted using hourly conversion rate from openexchangerates.org","chartName":"Bitcoin","bpi":{"USD":{"code":"USD","symbol":"&#36;","rate":"57,758.023","description":"United States Dollar","rate_float":57758.0232},"GBP":{"code":"GBP","symbol":"&pound;","rate":"44,069.892","description":"British Pound Sterling","rate_float":44069.8915},"EUR":{"code":"EUR","symbol":"&euro;","rate":"52,288.743","description":"Euro","rate_float":52288.7427},"CNY":{"code":"CNY","symbol":"&yen;","rate":"411,317.986","description":"Chinese Yuan","rate_float":411317.9864}}}