{"time":{"updated":"Jun 21, 2024 13:57:07 UTC","updatedISO":"2024-06-21T13:57:07+00:00","updateduk":"Jun 21, 2024 at 14:57 BST"},"disclaimer":"This data was produced from the CoinDesk Bitcoin Price Index (USD). Non-USD currency data converted using hourly conversion rate from openexchangerates.org","chartName":"Bitcoin","bpi":{"USD":{"code":"USD","symbol":"&#36;","rate":"63,583.324","description":"United States Dollar","rate_float":63583.3241},"GBP":{"code":"GBP","symbol":"&pound;","rate":"50,268.277","description":"British Pound Sterling","rate_float":50268.2766},"EUR":{"code":"EUR","symbol":"&euro;","rate":"59,453.269","description":"Euro","rate_float":59453.2693},"CNY":{"code":"CNY","symbol":"&yen;","rate":"461,659.441","description":"Chinese Yuan","rate_float":461659.4414}}}