{"time":{"updated":"Oct 9, 2024 15:12:20 UTC","updatedISO":"2024-10-09T15:12:20+00:00","updateduk":"Oct 9, 2024 at 16:12 BST"},"disclaimer":"This data was produced from the CoinDesk Bitcoin Price Index (USD). Non-USD currency data converted using hourly conversion rate from openexchangerates.org","chartName":"Bitcoin","bpi":{"USD":{"code":"USD","symbol":"&#36;","rate":"61,961.835","description":"United States Dollar","rate_float":61961.8347},"GBP":{"code":"GBP","symbol":"&pound;","rate":"47,393.058","description":"British Pound Sterling","rate_float":47393.0583},"EUR":{"code":"EUR","symbol":"&euro;","rate":"56,598.728","description":"Euro","rate_float":56598.7281},"CNY":{"code":"CNY","symbol":"&yen;","rate":"438,714.574","description":"Chinese Yuan","rate_float":438714.5744}}}