{"time":{"updated":"Nov 30, 2024 03:36:33 UTC","updatedISO":"2024-11-30T03:36:33+00:00","updateduk":"Nov 30, 2024 at 03:36 GMT"},"disclaimer":"This data was produced from the CoinDesk Bitcoin Price Index (USD). Non-USD currency data converted using hourly conversion rate from openexchangerates.org","chartName":"Bitcoin","bpi":{"USD":{"code":"USD","symbol":"&#36;","rate":"96,509.103","description":"United States Dollar","rate_float":96509.1029},"GBP":{"code":"GBP","symbol":"&pound;","rate":"75,794.486","description":"British Pound Sterling","rate_float":75794.4855},"EUR":{"code":"EUR","symbol":"&euro;","rate":"91,219.632","description":"Euro","rate_float":91219.6319},"CNY":{"code":"CNY","symbol":"&yen;","rate":"698,889.97","description":"Chinese Yuan","rate_float":698889.9701}}}