{"time":{"updated":"Mar 17, 2024 20:46:57 UTC","updatedISO":"2024-03-17T20:46:57+00:00","updateduk":"Mar 17, 2024 at 20:46 GMT"},"disclaimer":"This data was produced from the CoinDesk Bitcoin Price Index (USD). Non-USD currency data converted using hourly conversion rate from openexchangerates.org","chartName":"Bitcoin","bpi":{"USD":{"code":"USD","symbol":"&#36;","rate":"68,502.829","description":"United States Dollar","rate_float":68502.8288},"GBP":{"code":"GBP","symbol":"&pound;","rate":"53,791.024","description":"British Pound Sterling","rate_float":53791.0243},"EUR":{"code":"EUR","symbol":"&euro;","rate":"62,938.207","description":"Euro","rate_float":62938.207},"CNY":{"code":"CNY","symbol":"&yen;","rate":"492,939.506","description":"Chinese Yuan","rate_float":492939.506}}}