{"time":{"updated":"Aug 28, 2024 18:44:20 UTC","updatedISO":"2024-08-28T18:44:20+00:00","updateduk":"Aug 28, 2024 at 19:44 BST"},"disclaimer":"This data was produced from the CoinDesk Bitcoin Price Index (USD). Non-USD currency data converted using hourly conversion rate from openexchangerates.org","chartName":"Bitcoin","bpi":{"USD":{"code":"USD","symbol":"&#36;","rate":"58,889.434","description":"United States Dollar","rate_float":58889.4336},"GBP":{"code":"GBP","symbol":"&pound;","rate":"44,713.923","description":"British Pound Sterling","rate_float":44713.9225},"EUR":{"code":"EUR","symbol":"&euro;","rate":"53,020.572","description":"Euro","rate_float":53020.5715},"CNY":{"code":"CNY","symbol":"&yen;","rate":"419,610.77","description":"Chinese Yuan","rate_float":419610.7703}}}