{"time":{"updated":"Oct 4, 2024 18:37:05 UTC","updatedISO":"2024-10-04T18:37:05+00:00","updateduk":"Oct 4, 2024 at 19:37 BST"},"disclaimer":"This data was produced from the CoinDesk Bitcoin Price Index (USD). Non-USD currency data converted using hourly conversion rate from openexchangerates.org","chartName":"Bitcoin","bpi":{"USD":{"code":"USD","symbol":"&#36;","rate":"62,201.898","description":"United States Dollar","rate_float":62201.8978},"GBP":{"code":"GBP","symbol":"&pound;","rate":"47,402.387","description":"British Pound Sterling","rate_float":47402.3869},"EUR":{"code":"EUR","symbol":"&euro;","rate":"56,712.332","description":"Euro","rate_float":56712.3316},"CNY":{"code":"CNY","symbol":"&yen;","rate":"438,498.499","description":"Chinese Yuan","rate_float":438498.499}}}