{"time":{"updated":"May 13, 2024 15:15:56 UTC","updatedISO":"2024-05-13T15:15:56+00:00","updateduk":"May 13, 2024 at 16:15 BST"},"disclaimer":"This data was produced from the CoinDesk Bitcoin Price Index (USD). Non-USD currency data converted using hourly conversion rate from openexchangerates.org","chartName":"Bitcoin","bpi":{"USD":{"code":"USD","symbol":"&#36;","rate":"62,974.612","description":"United States Dollar","rate_float":62974.6116},"GBP":{"code":"GBP","symbol":"&pound;","rate":"50,120.801","description":"British Pound Sterling","rate_float":50120.8006},"EUR":{"code":"EUR","symbol":"&euro;","rate":"58,285.585","description":"Euro","rate_float":58285.585},"CNY":{"code":"CNY","symbol":"&yen;","rate":"455,520.556","description":"Chinese Yuan","rate_float":455520.5555}}}