{"time":{"updated":"Apr 2, 2024 14:38:15 UTC","updatedISO":"2024-04-02T14:38:15+00:00","updateduk":"Apr 2, 2024 at 15:38 BST"},"disclaimer":"This data was produced from the CoinDesk Bitcoin Price Index (USD). Non-USD currency data converted using hourly conversion rate from openexchangerates.org","chartName":"Bitcoin","bpi":{"USD":{"code":"USD","symbol":"&#36;","rate":"66,072.145","description":"United States Dollar","rate_float":66072.145},"GBP":{"code":"GBP","symbol":"&pound;","rate":"52,599.969","description":"British Pound Sterling","rate_float":52599.9685},"EUR":{"code":"EUR","symbol":"&euro;","rate":"61,377.389","description":"Euro","rate_float":61377.3887},"CNY":{"code":"CNY","symbol":"&yen;","rate":"478,071.612","description":"Chinese Yuan","rate_float":478071.6121}}}