{"time":{"updated":"Feb 13, 2024 02:54:52 UTC","updatedISO":"2024-02-13T02:54:52+00:00","updateduk":"Feb 13, 2024 at 02:54 GMT"},"disclaimer":"This data was produced from the CoinDesk Bitcoin Price Index (USD). Non-USD currency data converted using hourly conversion rate from openexchangerates.org","chartName":"Bitcoin","bpi":{"USD":{"code":"USD","symbol":"&#36;","rate":"49,924.449","description":"United States Dollar","rate_float":49924.449},"GBP":{"code":"GBP","symbol":"&pound;","rate":"39,556.189","description":"British Pound Sterling","rate_float":39556.1894},"EUR":{"code":"EUR","symbol":"&euro;","rate":"46,367.382","description":"Euro","rate_float":46367.3819},"CNY":{"code":"CNY","symbol":"&yen;","rate":"359,096.577","description":"Chinese Yuan","rate_float":359096.5767}}}