{"time":{"updated":"Dec 21, 2024 03:38:53 UTC","updatedISO":"2024-12-21T03:38:53+00:00","updateduk":"Dec 21, 2024 at 03:38 GMT"},"disclaimer":"This data was produced from the CoinDesk Bitcoin Price Index (USD). Non-USD currency data converted using hourly conversion rate from openexchangerates.org","chartName":"Bitcoin","bpi":{"USD":{"code":"USD","symbol":"&#36;","rate":"97,251.244","description":"United States Dollar","rate_float":97251.2436},"GBP":{"code":"GBP","symbol":"&pound;","rate":"77,777.655","description":"British Pound Sterling","rate_float":77777.6546},"EUR":{"code":"EUR","symbol":"&euro;","rate":"93,665.785","description":"Euro","rate_float":93665.7847},"CNY":{"code":"CNY","symbol":"&yen;","rate":"709,856.277","description":"Chinese Yuan","rate_float":709856.2773}}}