{"time":{"updated":"Nov 10, 2024 05:28:29 UTC","updatedISO":"2024-11-10T05:28:29+00:00","updateduk":"Nov 10, 2024 at 05:28 GMT"},"disclaimer":"This data was produced from the CoinDesk Bitcoin Price Index (USD). Non-USD currency data converted using hourly conversion rate from openexchangerates.org","chartName":"Bitcoin","bpi":{"USD":{"code":"USD","symbol":"&#36;","rate":"79,365.824","description":"United States Dollar","rate_float":79365.8235},"GBP":{"code":"GBP","symbol":"&pound;","rate":"61,440.576","description":"British Pound Sterling","rate_float":61440.5761},"EUR":{"code":"EUR","symbol":"&euro;","rate":"74,045.615","description":"Euro","rate_float":74045.6149},"CNY":{"code":"CNY","symbol":"&yen;","rate":"569,783.12","description":"Chinese Yuan","rate_float":569783.1199}}}