{"time":{"updated":"Sep 5, 2024 15:50:14 UTC","updatedISO":"2024-09-05T15:50:14+00:00","updateduk":"Sep 5, 2024 at 16:50 BST"},"disclaimer":"This data was produced from the CoinDesk Bitcoin Price Index (USD). Non-USD currency data converted using hourly conversion rate from openexchangerates.org","chartName":"Bitcoin","bpi":{"USD":{"code":"USD","symbol":"&#36;","rate":"56,061.497","description":"United States Dollar","rate_float":56061.4966},"GBP":{"code":"GBP","symbol":"&pound;","rate":"42,609.653","description":"British Pound Sterling","rate_float":42609.6526},"EUR":{"code":"EUR","symbol":"&euro;","rate":"50,597.239","description":"Euro","rate_float":50597.2386},"CNY":{"code":"CNY","symbol":"&yen;","rate":"397,604.952","description":"Chinese Yuan","rate_float":397604.952}}}