{"time":{"updated":"Jul 16, 2024 13:30:00 UTC","updatedISO":"2024-07-16T13:30:00+00:00","updateduk":"Jul 16, 2024 at 14:30 BST"},"disclaimer":"This data was produced from the CoinDesk Bitcoin Price Index (USD). Non-USD currency data converted using hourly conversion rate from openexchangerates.org","chartName":"Bitcoin","bpi":{"USD":{"code":"USD","symbol":"&#36;","rate":"63,981.827","description":"United States Dollar","rate_float":63981.8268},"GBP":{"code":"GBP","symbol":"&pound;","rate":"49,416.428","description":"British Pound Sterling","rate_float":49416.4279},"EUR":{"code":"EUR","symbol":"&euro;","rate":"58,802.306","description":"Euro","rate_float":58802.3059},"CNY":{"code":"CNY","symbol":"&yen;","rate":"464,021.8","description":"Chinese Yuan","rate_float":464021.8004}}}