{"time":{"updated":"Jan 27, 2025 07:47:57 UTC","updatedISO":"2025-01-27T07:47:57+00:00","updateduk":"Jan 27, 2025 at 07:47 GMT"},"disclaimer":"This data was produced from the CoinDesk Bitcoin Price Index (USD). Non-USD currency data converted using hourly conversion rate from openexchangerates.org","chartName":"Bitcoin","bpi":{"USD":{"code":"USD","symbol":"&#36;","rate":"99,207.043","description":"United States Dollar","rate_float":99207.0427},"GBP":{"code":"GBP","symbol":"&pound;","rate":"79,671.886","description":"British Pound Sterling","rate_float":79671.8863},"EUR":{"code":"EUR","symbol":"&euro;","rate":"94,849.572","description":"Euro","rate_float":94849.5717},"CNY":{"code":"CNY","symbol":"&yen;","rate":"720,907.817","description":"Chinese Yuan","rate_float":720907.8171}}}