{"time":{"updated":"Feb 25, 2024 17:46:02 UTC","updatedISO":"2024-02-25T17:46:02+00:00","updateduk":"Feb 25, 2024 at 17:46 GMT"},"disclaimer":"This data was produced from the CoinDesk Bitcoin Price Index (USD). Non-USD currency data converted using hourly conversion rate from openexchangerates.org","chartName":"Bitcoin","bpi":{"USD":{"code":"USD","symbol":"&#36;","rate":"51,529.057","description":"United States Dollar","rate_float":51529.057},"GBP":{"code":"GBP","symbol":"&pound;","rate":"40,641.276","description":"British Pound Sterling","rate_float":40641.2764},"EUR":{"code":"EUR","symbol":"&euro;","rate":"47,555.497","description":"Euro","rate_float":47555.4968},"CNY":{"code":"CNY","symbol":"&yen;","rate":"370,746.412","description":"Chinese Yuan","rate_float":370746.4123}}}