{"time":{"updated":"Apr 16, 2024 23:27:26 UTC","updatedISO":"2024-04-16T23:27:26+00:00","updateduk":"Apr 17, 2024 at 00:27 BST"},"disclaimer":"This data was produced from the CoinDesk Bitcoin Price Index (USD). Non-USD currency data converted using hourly conversion rate from openexchangerates.org","chartName":"Bitcoin","bpi":{"USD":{"code":"USD","symbol":"&#36;","rate":"63,948.918","description":"United States Dollar","rate_float":63948.9183},"GBP":{"code":"GBP","symbol":"&pound;","rate":"51,448.695","description":"British Pound Sterling","rate_float":51448.6953},"EUR":{"code":"EUR","symbol":"&euro;","rate":"60,216.668","description":"Euro","rate_float":60216.6676},"CNY":{"code":"CNY","symbol":"&yen;","rate":"462,811.112","description":"Chinese Yuan","rate_float":462811.1115}}}