{"time":{"updated":"Jun 23, 2024 22:46:03 UTC","updatedISO":"2024-06-23T22:46:03+00:00","updateduk":"Jun 23, 2024 at 23:46 BST"},"disclaimer":"This data was produced from the CoinDesk Bitcoin Price Index (USD). Non-USD currency data converted using hourly conversion rate from openexchangerates.org","chartName":"Bitcoin","bpi":{"USD":{"code":"USD","symbol":"&#36;","rate":"63,659.406","description":"United States Dollar","rate_float":63659.4061},"GBP":{"code":"GBP","symbol":"&pound;","rate":"50,358.283","description":"British Pound Sterling","rate_float":50358.2825},"EUR":{"code":"EUR","symbol":"&euro;","rate":"59,537.587","description":"Euro","rate_float":59537.5869},"CNY":{"code":"CNY","symbol":"&yen;","rate":"462,250.046","description":"Chinese Yuan","rate_float":462250.0457}}}