{"time":{"updated":"Jan 25, 2024 17:06:21 UTC","updatedISO":"2024-01-25T17:06:21+00:00","updateduk":"Jan 25, 2024 at 17:06 GMT"},"disclaimer":"This data was produced from the CoinDesk Bitcoin Price Index (USD). Non-USD currency data converted using hourly conversion rate from openexchangerates.org","chartName":"Bitcoin","bpi":{"USD":{"code":"USD","symbol":"&#36;","rate":"39,698.83","description":"United States Dollar","rate_float":39698.83},"GBP":{"code":"GBP","symbol":"&pound;","rate":"31,259.137","description":"British Pound Sterling","rate_float":31259.1367},"EUR":{"code":"EUR","symbol":"&euro;","rate":"36,649.92","description":"Euro","rate_float":36649.9202},"CNY":{"code":"CNY","symbol":"&yen;","rate":"281,297.97","description":"Chinese Yuan","rate_float":281297.97}}}