{"time":{"updated":"Jan 2, 2025 04:15:35 UTC","updatedISO":"2025-01-02T04:15:35+00:00","updateduk":"Jan 2, 2025 at 04:15 GMT"},"disclaimer":"This data was produced from the CoinDesk Bitcoin Price Index (USD). Non-USD currency data converted using hourly conversion rate from openexchangerates.org","chartName":"Bitcoin","bpi":{"USD":{"code":"USD","symbol":"&#36;","rate":"95,458.339","description":"United States Dollar","rate_float":95458.3388},"GBP":{"code":"GBP","symbol":"&pound;","rate":"76,126.116","description":"British Pound Sterling","rate_float":76126.116},"EUR":{"code":"EUR","symbol":"&euro;","rate":"91,579.962","description":"Euro","rate_float":91579.962},"CNY":{"code":"CNY","symbol":"&yen;","rate":"696,712.232","description":"Chinese Yuan","rate_float":696712.2318}}}